HW4/Q3/400521477_Q3.v
module sequence_counter (
  input wire clk,
  input wire rst,
  output reg [2:0] state
);
reg [2:0] nextState;
parameter [2:0] S5 = 3'b101;
parameter [2:0] S4 = 3'b100;
parameter [2:0] S7 = 3'b111;
parameter [2:0] S6 = 3'b110;
parameter [2:0] S1 = 3'b001;
parameter [2:0] S0 = 3'b000;
parameter [2:0] S3 = 3'b011;
parameter [2:0] S2 = 3'b010;

always @(negedge rst)
begin
    state <= S5;
end
always @(posedge clk)
begin
    state <= nextState;
end

always @(*)
begin
    case(state)
    3'b101:
    begin
    nextState = S4;
 
    end

    3'b100:
    begin
    nextState = S7;
 
    end
    
    3'b111:
    begin
    nextState = S6;
 
    end

    3'b110:
    begin
    nextState = S1;
 
    end

    3'b001:
    begin
    nextState = S0;
 
    end

    3'b000:
    begin
    nextState = S3;
 
    end

    3'b011:
    begin
    nextState = S2;
 
    end

    3'b010:
    begin
    nextState = S5;
 
    end
    default:begin
    end
    endcase
end

endmodule

HW4/Q3/400521477_T3.v
`timescale 1ms/1ms
`include "400521477_Q3.v"
module sequence_counter_tb;
    reg clk;
    reg rst;
    wire [2:0] state;

    sequence_counter inst(
        .clk(clk),
        .rst(rst),
        .state(state)
    );
    initial
    begin
        $dumpfile("4005214477_Q3.vcd");
        $dumpvars(0,sequence_counter_tb);
    rst = 1;
    rst = 0;
    clk = 0;
    #5
    
    repeat (100)
    begin
        #5 clk = ~clk;
        $display("state = %b", state);
    end
    end
endmodule

HW4/Q3/4005214477_Q3.vcd
$date
	Tue Jan 16 15:24:04 2024
$end
$version
	Icarus Verilog
$end
$timescale
	1ms
$end
$scope module sequence_counter_tb $end
$var wire 3 ! state [2:0] $end
$var reg 1 " clk $end
$var reg 1 # rst $end
$scope module inst $end
$var wire 1 " clk $end
$var wire 1 # rst $end
$var parameter 3 $ S0 $end
$var parameter 3 % S1 $end
$var parameter 3 & S2 $end
$var parameter 3 ' S3 $end
$var parameter 3 ( S4 $end
$var parameter 3 ) S5 $end
$var parameter 3 * S6 $end
$var parameter 3 + S7 $end
$var reg 3 , nextState [2:0] $end
$var reg 3 - state [2:0] $end
$upscope $end
$upscope $end
$enddefinitions $end
$comment Show the parameter values. $end
$dumpall
b111 +
b110 *
b101 )
b100 (
b11 '
b10 &
b1 %
b0 $
$end
#0
$dumpvars
b101 -
b100 ,
0#
0"
b101 !
$end
#10
b111 ,
b100 !
b100 -
1"
#15
0"
#20
b110 ,
b111 !
b111 -
1"
#25
0"
#30
b1 ,
b110 !
b110 -
1"
#35
0"
#40
b0 ,
b1 !
b1 -
1"
#45
0"
#50
b11 ,
b0 !
b0 -
1"
#55
0"
#60
b10 ,
b11 !
b11 -
1"
#65
0"
#70
b101 ,
b10 !
b10 -
1"
#75
0"
#80
b100 ,
b101 !
b101 -
1"
#85
0"
#90
b111 ,
b100 !
b100 -
1"
#95
0"
#100
b110 ,
b111 !
b111 -
1"
#105
0"
#110
b1 ,
b110 !
b110 -
1"
#115
0"
#120
b0 ,
b1 !
b1 -
1"
#125
0"
#130
b11 ,
b0 !
b0 -
1"
#135
0"
#140
b10 ,
b11 !
b11 -
1"
#145
0"
#150
b101 ,
b10 !
b10 -
1"
#155
0"
#160
b100 ,
b101 !
b101 -
1"
#165
0"
#170
b111 ,
b100 !
b100 -
1"
#175
0"
#180
b110 ,
b111 !
b111 -
1"
#185
0"
#190
b1 ,
b110 !
b110 -
1"
#195
0"
#200
b0 ,
b1 !
b1 -
1"
#205
0"
#210
b11 ,
b0 !
b0 -
1"
#215
0"
#220
b10 ,
b11 !
b11 -
1"
#225
0"
#230
b101 ,
b10 !
b10 -
1"
#235
0"
#240
b100 ,
b101 !
b101 -
1"
#245
0"
#250
b111 ,
b100 !
b100 -
1"
#255
0"
#260
b110 ,
b111 !
b111 -
1"
#265
0"
#270
b1 ,
b110 !
b110 -
1"
#275
0"
#280
b0 ,
b1 !
b1 -
1"
#285
0"
#290
b11 ,
b0 !
b0 -
1"
#295
0"
#300
b10 ,
b11 !
b11 -
1"
#305
0"
#310
b101 ,
b10 !
b10 -
1"
#315
0"
#320
b100 ,
b101 !
b101 -
1"
#325
0"
#330
b111 ,
b100 !
b100 -
1"
#335
0"
#340
b110 ,
b111 !
b111 -
1"
#345
0"
#350
b1 ,
b110 !
b110 -
1"
#355
0"
#360
b0 ,
b1 !
b1 -
1"
#365
0"
#370
b11 ,
b0 !
b0 -
1"
#375
0"
#380
b10 ,
b11 !
b11 -
1"
#385
0"
#390
b101 ,
b10 !
b10 -
1"
#395
0"
#400
b100 ,
b101 !
b101 -
1"
#405
0"
#410
b111 ,
b100 !
b100 -
1"
#415
0"
#420
b110 ,
b111 !
b111 -
1"
#425
0"
#430
b1 ,
b110 !
b110 -
1"
#435
0"
#440
b0 ,
b1 !
b1 -
1"
#445
0"
#450
b11 ,
b0 !
b0 -
1"
#455
0"
#460
b10 ,
b11 !
b11 -
1"
#465
0"
#470
b101 ,
b10 !
b10 -
1"
#475
0"
#480
b100 ,
b101 !
b101 -
1"
#485
0"
#490
b111 ,
b100 !
b100 -
1"
#495
0"
#500
b110 ,
b111 !
b111 -
1"
