HW4/Q1/400521477_Q1.v
module top(
    input [3:0] A,
    input [3:0] B,
    input clk,
    input [1:0] c,
    input EN,
    output reg Out_c,
    output reg [3:0] Out_bits
    
);
wire A_equal_B;
wire A_greater_than_B;
wire A_less_than_B;
wire out_c;
wire [3:0] out_bits;
FourBitComparator inst(
        .A(A),
        .B(B),
        .A_equal_B(A_equal_B),
        .A_greater_than_B(A_greater_than_B),
        .A_less_than_B(A_less_than_B)
);

controller ins(
    .A_equal_B(A_equal_B),
    .A_greater_than_B(A_greater_than_B),
    .A_less_than_B(A_less_than_B),
    .clk(clk),
    .c(c),
    .EN(EN),
    .out_c(out_c),
    .out_bits(out_bits)
);

always @(posedge clk)
begin
    if (EN == 1)
    begin
    Out_bits <= 4'b0000;
    Out_c <= out_c;
    if (out_c)
    Out_bits <= A;
    end
end

endmodule
module OneBitComparator (
    input wire A,
    input wire B,
    output wire A_equal_B,
    output wire A_greater_than_B,
    output wire A_less_than_B
);

assign A_equal_B = ~(A ^ B);
assign A_greater_than_B = (A & ~B);
assign A_less_than_B = (~A & B);

endmodule

module FourBitComparator (
    input [3:0] A,
    input [3:0] B,
    output A_equal_B,
    output A_greater_than_B,
    output A_less_than_B
);

wire [3:0] equal_bits, greater_than_bits, less_than_bits;

OneBitComparator comp_0 (.A(A[0]), .B(B[0]), .A_equal_B(equal_bits[0]), .A_greater_than_B(greater_than_bits[0]), .A_less_than_B(less_than_bits[0]));
OneBitComparator comp_1 (.A(A[1]), .B(B[1]), .A_equal_B(equal_bits[1]), .A_greater_than_B(greater_than_bits[1]), .A_less_than_B(less_than_bits[1]));
OneBitComparator comp_2 (.A(A[2]), .B(B[2]), .A_equal_B(equal_bits[2]), .A_greater_than_B(greater_than_bits[2]), .A_less_than_B(less_than_bits[2]));
OneBitComparator comp_3 (.A(A[3]), .B(B[3]), .A_equal_B(equal_bits[3]), .A_greater_than_B(greater_than_bits[3]), .A_less_than_B(less_than_bits[3]));
assign A_equal_B = &equal_bits;
assign A_greater_than_B = greater_than_bits[3] ? 1'b1:
                        ~less_than_bits[3] & greater_than_bits[2] ? 1'b1:
                         ~less_than_bits[2] & greater_than_bits[1] ? 1'b1:
                         ~less_than_bits[1] & greater_than_bits[0] ? 1'b1: 1'b0;  
assign A_less_than_B = less_than_bits[3] ? 1'b1:
                        ~greater_than_bits[3] & less_than_bits[2] ? 1'b1:
                       ~greater_than_bits[2] & less_than_bits[1] ? 1'b1:
                        ~greater_than_bits[1] & less_than_bits[0] ? 1'b1: 1'b0;

endmodule




module controller(
    input A_equal_B,
    input A_greater_than_B,
    input A_less_than_B,
    input clk,
    input [1:0] c,
    input EN,
    output reg out_c,
    output reg [3:0] out_bits
);

always @(posedge clk)
begin
    if (EN)
    begin
    case(c)
    2'b00:
    begin
    out_c <= A_greater_than_B;
    end
    2'b01:
    begin
    out_c <= A_equal_B;
    end
    2'b10:
    begin
    out_c <= A_less_than_B;
    end
    default:begin
    end
    endcase
    end

    else
    begin
    out_c <= 0;
    end
end
endmodule

HW4/Q1/400521477_T1_top.v
`include "400521477_Q1.v"

module top_tb;
    reg [3:0] A;
    reg [3:0] B;
    reg clk;
    reg [1:0] c;
    reg EN;
    wire Out_c;
    wire [3:0] Out_bits;
    top inst(
        .A(A),
        .B(B),
        .clk(clk),
        .c(c),
        .EN(EN),
        .Out_c(Out_c),
        .Out_bits(Out_bits)
    );
    initial
    begin
        $dumpfile("4005214477_Q1_top.vcd");
        $dumpvars(0,top_tb);
        A = 4'b0111;
        B = 4'b0111;
        c = 2'b01;
        EN = 1;
        clk = 0;
        #10
        repeat(60)
        begin
          #5 clk = ~clk;
        end

        #20
        A = 4'b1000;
        B = 4'b0010;
        c = 2'b00;
        EN = 1;
        clk = 0;
        #10
        repeat(60)
        begin
          #5 clk = ~clk;
        end

        $finish;
        //$display("Out_c = %b", Out_c);
        //$display("Out_bits = %b", Out_bits);
    end
endmodule

HW4/Q1/4005214477_Q1_top.vcd
$date
	Mon Jan 08 15:49:55 2024
$end
$version
	Icarus Verilog
$end
$timescale
	1s
$end
$scope module top_tb $end
$var wire 1 ! Out_c $end
$var wire 4 " Out_bits [3:0] $end
$var reg 4 # A [3:0] $end
$var reg 4 $ B [3:0] $end
$var reg 1 % EN $end
$var reg 2 & c [1:0] $end
$var reg 1 ' clk $end
$scope module inst $end
$var wire 4 ( A [3:0] $end
$var wire 4 ) B [3:0] $end
$var wire 1 % EN $end
$var wire 2 * c [1:0] $end
$var wire 1 ' clk $end
$var wire 1 + out_c $end
$var wire 4 , out_bits [3:0] $end
$var wire 1 - A_less_than_B $end
$var wire 1 . A_greater_than_B $end
$var wire 1 / A_equal_B $end
$var reg 4 0 Out_bits [3:0] $end
$var reg 1 ! Out_c $end
$scope module ins $end
$var wire 1 % EN $end
$var wire 2 1 c [1:0] $end
$var wire 1 ' clk $end
$var wire 1 - A_less_than_B $end
$var wire 1 . A_greater_than_B $end
$var wire 1 / A_equal_B $end
$var reg 4 2 out_bits [3:0] $end
$var reg 1 + out_c $end
$upscope $end
$scope module inst $end
$var wire 4 3 A [3:0] $end
$var wire 4 4 B [3:0] $end
$var wire 4 5 less_than_bits [3:0] $end
$var wire 4 6 greater_than_bits [3:0] $end
$var wire 4 7 equal_bits [3:0] $end
$var wire 1 - A_less_than_B $end
$var wire 1 . A_greater_than_B $end
$var wire 1 / A_equal_B $end
$scope module comp_0 $end
$var wire 1 8 A $end
$var wire 1 9 A_equal_B $end
$var wire 1 : A_greater_than_B $end
$var wire 1 ; A_less_than_B $end
$var wire 1 < B $end
$upscope $end
$scope module comp_1 $end
$var wire 1 = A $end
$var wire 1 > A_equal_B $end
$var wire 1 ? A_greater_than_B $end
$var wire 1 @ A_less_than_B $end
$var wire 1 A B $end
$upscope $end
$scope module comp_2 $end
$var wire 1 B A $end
$var wire 1 C A_equal_B $end
$var wire 1 D A_greater_than_B $end
$var wire 1 E A_less_than_B $end
$var wire 1 F B $end
$upscope $end
$scope module comp_3 $end
$var wire 1 G A $end
$var wire 1 H A_equal_B $end
$var wire 1 I A_greater_than_B $end
$var wire 1 J A_less_than_B $end
$var wire 1 K B $end
$upscope $end
$upscope $end
$upscope $end
$upscope $end
$enddefinitions $end
$comment Show the parameter values. $end
$dumpall
$end
#0
$dumpvars
0K
0J
0I
1H
0G
1F
0E
0D
1C
1B
1A
0@
0?
1>
1=
1<
0;
0:
19
18
b1111 7
b0 6
b0 5
b111 4
b111 3
bx 2
b1 1
bx 0
1/
0.
0-
bx ,
x+
b1 *
b111 )
b111 (
0'
b1 &
1%
b111 $
b111 #
bx "
x!
$end
#15
1+
b0 "
b0 0
1'
#20
0'
#25
b111 "
b111 0
1!
1'
#30
0'
#35
b111 "
b111 0
1'
#40
0'
#45
b111 "
b111 0
1'
#50
0'
#55
b111 "
b111 0
1'
#60
0'
#65
b111 "
b111 0
1'
#70
0'
#75
b111 "
b111 0
1'
#80
0'
#85
b111 "
b111 0
1'
#90
0'
#95
b111 "
b111 0
1'
#100
0'
#105
b111 "
b111 0
1'
#110
0'
#115
b111 "
b111 0
1'
#120
0'
#125
b111 "
b111 0
1'
#130
0'
#135
b111 "
b111 0
1'
#140
0'
#145
b111 "
b111 0
1'
#150
0'
#155
b111 "
b111 0
1'
#160
0'
#165
b111 "
b111 0
1'
#170
0'
#175
b111 "
b111 0
1'
#180
0'
#185
b111 "
b111 0
1'
#190
0'
#195
b111 "
b111 0
1'
#200
0'
#205
b111 "
b111 0
1'
#210
0'
#215
b111 "
b111 0
1'
#220
0'
#225
b111 "
b111 0
1'
#230
0'
#235
b111 "
b111 0
1'
#240
0'
#245
b111 "
b111 0
1'
#250
0'
#255
b111 "
b111 0
1'
#260
0'
#265
b111 "
b111 0
1'
#270
0'
#275
b111 "
b111 0
1'
#280
0'
#285
b111 "
b111 0
1'
#290
0'
#295
b111 "
b111 0
1'
#300
0'
#305
b111 "
b111 0
1'
#310
0'
#330
1-
1.
0>
b10 5
1@
0/
b101 7
0H
b1000 6
1I
0<
0F
08
0=
0B
1G
b0 &
b0 *
b0 1
b10 $
b10 )
b10 4
b1000 #
b1000 (
b1000 3
#345
b1000 "
b1000 0
1'
#350
0'
#355
b1000 "
b1000 0
1'
#360
0'
#365
b1000 "
b1000 0
1'
#370
0'
#375
b1000 "
b1000 0
1'
#380
0'
#385
b1000 "
b1000 0
1'
#390
0'
#395
b1000 "
b1000 0
1'
#400
0'
#405
b1000 "
b1000 0
1'
#410
0'
#415
b1000 "
b1000 0
1'
#420
0'
#425
b1000 "
b1000 0
1'
#430
0'
#435
b1000 "
b1000 0
1'
#440
0'
#445
b1000 "
b1000 0
1'
#450
0'
#455
b1000 "
b1000 0
1'
#460
0'
#465
b1000 "
b1000 0
1'
#470
0'
#475
b1000 "
b1000 0
1'
#480
0'
#485
b1000 "
b1000 0
1'
#490
0'
#495
b1000 "
b1000 0
1'
#500
0'
#505
b1000 "
b1000 0
1'
#510
0'
#515
b1000 "
b1000 0
1'
#520
0'
#525
b1000 "
b1000 0
1'
#530
0'
#535
b1000 "
b1000 0
1'
#540
0'
#545
b1000 "
b1000 0
1'
#550
0'
#555
b1000 "
b1000 0
1'
#560
0'
#565
b1000 "
b1000 0
1'
#570
0'
#575
b1000 "
b1000 0
1'
#580
0'
#585
b1000 "
b1000 0
1'
#590
0'
#595
b1000 "
b1000 0
1'
#600
0'
#605
b1000 "
b1000 0
1'
#610
0'
#615
b1000 "
b1000 0
1'
#620
0'
#625
b1000 "
b1000 0
1'
#630
0'
#635
b1000 "
b1000 0
1'
