Project/CAD Final Project/Project.v
module DClock(
  input CLK,
  input rst,
  output reg [15:0] LED,
  output reg [7:0] SEG_DATA,
  output reg [4:0] SEG_SEL
  //output reg BUZZER
);
reg CLK10MS = 1'b0;
reg CLK1S = 1'b0;
reg [7:0] SEG_DATA_reg1, SEG_DATA_reg2, SEG_DATA_reg3, SEG_DATA_reg4;
reg COUNTER2, COUNTER3, COUNTER4;
reg [3:0] BCD1, BCD2, BCD3, BCD4;
//reg ALARM;
reg [15:0] count_div1 = 8'b00000000;
reg [7:0] count_div2 = 8'b00000000;
reg [3:0] counter1 = 4'b0000;
reg [3:0] counter2 = 4'b0000;
reg [3:0] counter3 = 4'b0000;
reg [3:0] counter4 = 4'b0000;
reg [2:0] RefreshSEG;
//reg idle;

always @(negedge rst)
begin
  BCD1 <= 4'b0000;
  BCD2 <= 4'b0000;
  BCD3 <= 4'b0000;
  BCD4 <= 4'b0000;
end
// 10 millisecond delay signal
always @(posedge CLK)
begin
  if (count_div1 < 2) //400000
    count_div1 <= count_div1 + 1;
  else begin
    count_div1 <= 0;
    CLK10MS <= ~CLK10MS;
  end
end

// 1 second delay signal
always @(posedge CLK10MS)
begin
  if (count_div2 < 40) //41
    count_div2 <= count_div2 + 1;
  else begin
    count_div2 <= 0;
    CLK1S <= ~CLK1S;
  end
end

// BCD counters
always @(posedge CLK1S)
begin
    if (counter1 < 9) begin
      counter1 = counter1 + 1;
      COUNTER2 = 0;
    end
    else begin
      counter1 = 0;
      COUNTER2 = 1;
    end
    BCD1 = counter1;
end

always @(posedge COUNTER2)
begin
    if (counter2 < 5) begin
      counter2 = counter2 + 1;
      COUNTER3 = 0;
    end
    else begin
      counter2 = 0;
      COUNTER3 = 1;
    end
    BCD2 = counter2;
end

always @(posedge COUNTER3)
begin
    if (counter3 < 9) begin
      counter3 = counter3 + 1;
      COUNTER3 = 0;
    end
    else begin
      counter3 = 0;
      COUNTER4 = 1;
    end
    BCD3 = counter3;
end

always @(posedge COUNTER4)
begin
    if (counter4 < 5) begin
      counter4 = counter4 + 1;
      COUNTER3 = 0;
    end
    else begin
      counter3 = 0;
    end
    BCD4 = counter4;
end

// BCD to 7 segment converters
always @(*)
begin
  case (BCD1)
    4'b0000: SEG_DATA_reg1 = 7'b0111111;
    4'b0001: SEG_DATA_reg1 = 7'b0000110;
    4'b0010: SEG_DATA_reg1 = 7'b1011011;
    4'b0011: SEG_DATA_reg1 = 7'b1001111;
    4'b0100: SEG_DATA_reg1 = 7'b1100110;
    4'b0101: SEG_DATA_reg1 = 7'b1101101;
    4'b0110: SEG_DATA_reg1 = 7'b1111101;
    4'b0111: SEG_DATA_reg1 = 7'b0000111;
    4'b1000: SEG_DATA_reg1 = 7'b1111111;
    4'b1001: SEG_DATA_reg1 = 7'b1101111;
    default: SEG_DATA_reg1 = 7'b0000000;
  endcase
end

always @(*)
begin
  case (BCD2)
    4'b0000: SEG_DATA_reg2 = 7'b0111111;
    4'b0001: SEG_DATA_reg2 = 7'b0000110;
    4'b0010: SEG_DATA_reg2 = 7'b1011011;
    4'b0011: SEG_DATA_reg2 = 7'b1001111;
    4'b0100: SEG_DATA_reg2 = 7'b1100110;
    4'b0101: SEG_DATA_reg2 = 7'b1101101;
    4'b0110: SEG_DATA_reg2 = 7'b1111101;
    4'b0111: SEG_DATA_reg2 = 7'b0000111;
    4'b1000: SEG_DATA_reg2 = 7'b1111111;
    4'b1001: SEG_DATA_reg2 = 7'b1101111;
    default: SEG_DATA_reg2 = 7'b0000000;
  endcase
end

always @(*)
begin
  case (BCD3)
    4'b0000: SEG_DATA_reg3 = 7'b0111111;
    4'b0001: SEG_DATA_reg3 = 7'b0000110;
    4'b0010: SEG_DATA_reg3 = 7'b1011011;
    4'b0011: SEG_DATA_reg3 = 7'b1001111;
    4'b0100: SEG_DATA_reg3 = 7'b1100110;
    4'b0101: SEG_DATA_reg3 = 7'b1101101;
    4'b0110: SEG_DATA_reg3 = 7'b1111101;
    4'b0111: SEG_DATA_reg3 = 7'b0000111;
    4'b1000: SEG_DATA_reg3 = 7'b1111111;
    4'b1001: SEG_DATA_reg3 = 7'b1101111;
    default: SEG_DATA_reg3 = 7'b0000000;
  endcase
end

always @(*)
begin
  case (BCD4)
    4'b0000: SEG_DATA_reg4 = 7'b0111111;
    4'b0001: SEG_DATA_reg4 = 7'b0000110;
    4'b0010: SEG_DATA_reg4 = 7'b1011011;
    4'b0011: SEG_DATA_reg4 = 7'b1001111;
    4'b0100: SEG_DATA_reg4 = 7'b1100110;
    4'b0101: SEG_DATA_reg4 = 7'b1101101;
    4'b0110: SEG_DATA_reg4 = 7'b1111101;
    4'b0111: SEG_DATA_reg4 = 7'b0000111;
    4'b1000: SEG_DATA_reg4 = 7'b1111111;
    4'b1001: SEG_DATA_reg4 = 7'b1101111;
    default: SEG_DATA_reg4 = 7'b0000000;
  endcase
end



always @(*)
begin
  LED = {BCD4, BCD3, BCD2, BCD1};
end

// Display refresher
always @(posedge CLK10MS)
begin
  if (RefreshSEG < 4)
    RefreshSEG <= RefreshSEG + 1;
  else 
    RefreshSEG <= 0;
  case (RefreshSEG)
    3'b000: begin
      SEG_SEL[4] <= 1'b0;
      SEG_SEL[0] <= 1'b1;
      SEG_DATA <= SEG_DATA_reg1;
    end
    3'b001: begin
      SEG_SEL[0] <= 1'b0;
      SEG_SEL[1] <= 1'b1;
      SEG_DATA <= SEG_DATA_reg2;
    end
    3'b010: begin
      SEG_SEL[1] <= 1'b0;
      SEG_SEL[2] <= 1'b1;
      SEG_DATA <= SEG_DATA_reg3;
    end
    3'b011: begin
      SEG_SEL[2] <= 1'b0;
      SEG_SEL[3] <= 1'b1;
      SEG_DATA <= SEG_DATA_reg4;
    end

    3'b100: begin
      SEG_SEL[3] <= 1'b0;
      SEG_SEL[4] <= 1'b1;
      SEG_DATA[0] <= BCD1[0];
      SEG_DATA[1] <= BCD1[0];
      SEG_DATA[7:2] <= 6'b000000;
    end
    default: begin
    end
  endcase
end

// Buzzer controller
/*always @(posedge CLK)
begin
  BUZZER <= 1'b0;
  if (idle) begin
    if (ALARM) begin
      BUZZER <= 1'b1;
      idle <= 1'b0;
    end
  end
  else begin
    if (!ALARM) idle <= 1'b1;
  end
end*/

endmodule

Project/CAD Final Project/Project_T.v
`include "Project.v"
`timescale 1ms/1ms
module DClock_tb;
    reg CLK;
    reg rst;
    wire [15:0] LED;
    wire [7:0] SEG_DATA;
    wire [4:0] SEG_SEL;
    //wire BUZZER;
    DClock inst(
        .CLK(CLK),
        .rst(rst),
        .LED(LED),
        .SEG_DATA(SEG_DATA),
        .SEG_SEL(SEG_SEL)
        //.BUZZER(BUZZER)
    );
    initial
    begin
        $dumpfile("Project.vcd");
        $dumpvars(0,DClock_tb);
        CLK = 0;
        rst = 1;
        #1
        rst = 0;
        repeat(100000)
        begin
        #1 CLK = ~CLK;
        
        //$display("LED = %b", LED);
        //$display("SEG_DATA = %b", SEG_DATA);
        //$display("SEG_SEL = %b", SEG_SEL);
        end
       
        $finish;
    end
endmodule

Project/CAD Final Project/Project.vcd
$date
	Wed Jan 24 17:28:03 2024
$end
$version
	Icarus Verilog
$end
$timescale
	1ms
$end
$scope module DClock_tb $end
$var wire 5 ! SEG_SEL [4:0] $end
$var wire 8 " SEG_DATA [7:0] $end
$var wire 16 # LED [15:0] $end
$var reg 1 $ CLK $end
$var reg 1 % rst $end
$scope module inst $end
$var wire 1 $ CLK $end
$var wire 1 % rst $end
$var reg 4 & BCD1 [3:0] $end
$var reg 4 ' BCD2 [3:0] $end
$var reg 4 ( BCD3 [3:0] $end
$var reg 4 ) BCD4 [3:0] $end
$var reg 1 * CLK10MS $end
$var reg 1 + CLK1S $end
$var reg 1 , COUNTER2 $end
$var reg 1 - COUNTER3 $end
$var reg 1 . COUNTER4 $end
$var reg 16 / LED [15:0] $end
$var reg 3 0 RefreshSEG [2:0] $end
$var reg 8 1 SEG_DATA [7:0] $end
$var reg 8 2 SEG_DATA_reg1 [7:0] $end
$var reg 8 3 SEG_DATA_reg2 [7:0] $end
$var reg 8 4 SEG_DATA_reg3 [7:0] $end
$var reg 8 5 SEG_DATA_reg4 [7:0] $end
$var reg 5 6 SEG_SEL [4:0] $end
$var reg 16 7 count_div1 [15:0] $end
$var reg 8 8 count_div2 [7:0] $end
$var reg 4 9 counter1 [3:0] $end
$var reg 4 : counter2 [3:0] $end
$var reg 4 ; counter3 [3:0] $end
$var reg 4 < counter4 [3:0] $end
$upscope $end
$upscope $end
$enddefinitions $end
$comment Show the parameter values. $end
$dumpall
$end
#0
$dumpvars
b0 <
b0 ;
b0 :
b0 9
b0 8
b0 7
bx 6
bx 5
bx 4
bx 3
bx 2
bx 1
bx 0
bx /
x.
x-
x,
0+
0*
bx )
bx (
bx '
bx &
1%
0$
bx #
bx "
bx !
$end
#1
b111111 5
b111111 4
b111111 3
b0 #
b0 /
b111111 2
b0 )
b0 (
b0 '
b0 &
0%
#2
b1 7
1$
#3
0$
#4
b10 7
1$
#5
0$
#6
b1 8
b0 0
1*
b0 7
1$
#7
0$
#8
b1 7
1$
#9
0$
#10
b10 7
1$
#11
0$
#12
0*
b0 7
1$
#13
0$
#14
b1 7
1$
#15
0$
#16
b10 7
1$
#17
0$
#18
b111111 "
b111111 1
b0xxx1 !
b0xxx1 6
b1 0
b10 8
1*
b0 7
1$
#19
0$
#20
b1 7
1$
#21
0$
#22
b10 7
1$
#23
0$
#24
0*
b0 7
1$
#25
0$
#26
b1 7
1$
#27
0$
#28
b10 7
1$
#29
0$
#30
b11 8
b0xx10 !
b0xx10 6
b10 0
1*
b0 7
1$
#31
0$
#32
b1 7
1$
#33
0$
#34
b10 7
1$
#35
0$
#36
0*
b0 7
1$
#37
0$
#38
b1 7
1$
#39
0$
#40
b10 7
1$
#41
0$
#42
b0x100 !
b0x100 6
b11 0
b100 8
1*
b0 7
1$
#43
0$
#44
b1 7
1$
#45
0$
#46
b10 7
1$
#47
0$
#48
0*
b0 7
1$
#49
0$
#50
b1 7
1$
#51
0$
#52
b10 7
1$
#53
0$
#54
b101 8
b1000 !
b1000 6
b100 0
1*
b0 7
1$
#55
0$
#56
b1 7
1$
#57
0$
#58
b10 7
1$
#59
0$
#60
0*
b0 7
1$
#61
0$
#62
b1 7
1$
#63
0$
#64
b10 7
1$
#65
0$
#66
b0 "
b0 1
b10000 !
b10000 6
b0 0
b110 8
1*
b0 7
1$
#67
0$
#68
b1 7
1$
#69
0$
#70
b10 7
1$
#71
0$
#72
0*
b0 7
1$
#73
0$
#74
b1 7
1$
#75
0$
#76
b10 7
1$
#77
0$
#78
b111 8
b111111 "
b111111 1
b1 !
b1 6
b1 0
1*
b0 7
1$
#79
0$
#80
b1 7
1$
#81
0$
#82
b10 7
1$
#83
0$
#84
0*
b0 7
1$
#85
0$
#86
b1 7
1$
#87
0$
#88
b10 7
1$
#89
0$
#90
b10 !
b10 6
b10 0
b1000 8
1*
b0 7
1$
#91
0$
#92
b1 7
1$
#93
0$
#94
b10 7
1$
#95
0$
#96
0*
b0 7
1$
#97
0$
#98
b1 7
1$
#99
0$
#100
b10 7
1$
#101
0$
#102
b1001 8
b100 !
b100 6
b11 0
1*
b0 7
1$
#103
0$
#104
b1 7
1$
#105
0$
#106
b10 7
1$
#107
0$
#108
0*
b0 7
1$
#109
0$
#110
b1 7
1$
#111
0$
#112
b10 7
1$
#113
0$
#114
b1000 !
b1000 6
b100 0
b1010 8
1*
b0 7
1$
#115
0$
#116
b1 7
1$
#117
0$
#118
b10 7
1$
#119
0$
#120
0*
b0 7
1$
#121
0$
#122
b1 7
1$
#123
0$
#124
b10 7
1$
#125
0$
#126
b1011 8
b0 "
b0 1
b10000 !
b10000 6
b0 0
1*
b0 7
1$
#127
0$
#128
b1 7
1$
#129
0$
#130
b10 7
1$
#131
0$
#132
0*
b0 7
1$
#133
0$
#134
b1 7
1$
#135
0$
#136
b10 7
1$
#137
0$
#138
b111111 "
b111111 1
b1 !
b1 6
b1 0
b1100 8
1*
b0 7
1$
#139
0$
#140
b1 7
1$
#141
0$
#142
b10 7
1$
#143
0$
#144
0*
b0 7
1$
#145
0$
#146
b1 7
1$
#147
0$
#148
b10 7
1$
#149
0$
#150
b1101 8
b10 !
b10 6
b10 0
1*
b0 7
1$
#151
0$
#152
b1 7
1$
#153
0$
#154
b10 7
1$
#155
0$
#156
0*
b0 7
1$
#157
0$
#158
b1 7
1$
#159
0$
#160
b10 7
1$
#161
0$
#162
b100 !
b100 6
b11 0
b1110 8
1*
b0 7
1$
#163
0$
#164
b1 7
1$
#165
0$
#166
b10 7
1$
#167
0$
#168
0*
b0 7
1$
#169
0$
#170
b1 7
1$
#171
0$
#172
b10 7
1$
#173
0$
#174
b1111 8
b1000 !
b1000 6
b100 0
1*
b0 7
1$
#175
0$
#176
b1 7
1$
#177
0$
#178
b10 7
1$
#179
0$
#180
0*
b0 7
1$
#181
0$
#182
b1 7
1$
#183
0$
#184
b10 7
1$
#185
0$
#186
b0 "
b0 1
b10000 !
b10000 6
b0 0
b10000 8
1*
b0 7
1$
#187
0$
#188
b1 7
1$
#189
0$
#190
b10 7
1$
#191
0$
#192
0*
b0 7
1$
#193
0$
#194
b1 7
1$
#195
0$
#196
b10 7
1$
#197
0$
#198
b10001 8
b111111 "
b111111 1
b1 !
b1 6
b1 0
1*
b0 7
1$
#199
0$
#200
b1 7
1$
#201
0$
#202
b10 7
1$
#203
0$
#204
0*
b0 7
1$
#205
0$
#206
b1 7
1$
#207
0$
#208
b10 7
1$
#209
0$
#210
b10 !
b10 6
b10 0
b10010 8
1*
b0 7
1$
#211
0$
#212
b1 7
1$
#213
0$
#214
b10 7
1$
#215
0$
#216
0*
b0 7
1$
#217
0$
#218
b1 7
1$
#219
0$
#220
b10 7
1$
#221
0$
#222
b10011 8
b100 !
b100 6
b11 0
1*
b0 7
1$
#223
0$
#224
b1 7
1$
#225
0$
#226
b10 7
1$
#227
0$
#228
0*
b0 7
1$
#229
0$
#230
b1 7
1$
#231
0$
#232
b10 7
1$
#233
0$
#234
b1000 !
b1000 6
b100 0
b10100 8
1*
b0 7
1$
#235
0$
#236
b1 7
1$
#237
0$
#238
b10 7
1$
#239
0$
#240
0*
b0 7
1$
#241
0$
#242
b1 7
1$
#243
0$
#244
b10 7
1$
#245
0$
#246
b10101 8
b0 "
b0 1
b10000 !
b10000 6
b0 0
1*
b0 7
1$
#247
0$
#248
b1 7
1$
#249
0$
#250
b10 7
1$
#251
0$
#252
0*
b0 7
1$
#253
0$
#254
b1 7
1$
#255
0$
#256
b10 7
1$
#257
0$
#258
b111111 "
b111111 1
b1 !
b1 6
b1 0
b10110 8
1*
b0 7
1$
#259
0$
#260
b1 7
1$
#261
0$
#262
b10 7
1$
#263
0$
#264
0*
b0 7
1$
#265
0$
#266
b1 7
1$
#267
0$
#268
b10 7
1$
#269
0$
#270
b10111 8
b10 !
b10 6
b10 0
1*
b0 7
1$
#271
0$
#272
b1 7
1$
#273
0$
#274
b10 7
1$
#275
0$
#276
0*
b0 7
1$
#277
0$
#278
b1 7
1$
#279
0$
#280
b10 7
1$
#281
0$
#282
b100 !
b100 6
b11 0
b11000 8
1*
b0 7
1$
#283
0$
#284
b1 7
1$
#285
0$
#286
b10 7
1$
#287
0$
#288
0*
b0 7
1$
#289
0$
#290
b1 7
1$
#291
0$
#292
b10 7
1$
#293
0$
#294
b11001 8
b1000 !
b1000 6
b100 0
1*
b0 7
1$
#295
0$
#296
b1 7
1$
#297
0$
#298
b10 7
1$
#299
0$
#300
0*
b0 7
1$
#301
0$
#302
b1 7
1$
#303
0$
#304
b10 7
1$
#305
0$
#306
b0 "
b0 1
b10000 !
b10000 6
b0 0
b11010 8
1*
b0 7
1$
#307
0$
#308
b1 7
1$
#309
0$
#310
b10 7
1$
#311
0$
#312
0*
b0 7
1$
#313
0$
#314
b1 7
1$
#315
0$
#316
b10 7
1$
#317
0$
#318
b11011 8
b111111 "
b111111 1
b1 !
b1 6
b1 0
1*
b0 7
1$
#319
0$
#320
b1 7
1$
#321
0$
#322
b10 7
1$
#323
0$
#324
0*
b0 7
1$
#325
0$
#326
b1 7
1$
#327
0$
#328
b10 7
1$
#329
0$
#330
b10 !
b10 6
b10 0
b11100 8
1*
b0 7
1$
#331
0$
#332
b1 7
1$
#333
0$
#334
b10 7
1$
#335
0$
#336
0*
b0 7
1$
#337
0$
#338
b1 7
1$
#339
0$
#340
b10 7
1$
#341
0$
#342
b11101 8
b100 !
b100 6
b11 0
1*
b0 7
1$
#343
0$
#344
b1 7
1$
#345
0$
#346
b10 7
1$
#347
0$
#348
0*
b0 7
1$
#349
0$
#350
b1 7
1$
#351
0$
#352
b10 7
1$
#353
0$
#354
b1000 !
b1000 6
b100 0
b11110 8
1*
b0 7
1$
#355
0$
#356
b1 7
1$
#357
0$
#358
b10 7
1$
#359
0$
#360
0*
b0 7
1$
#361
0$
#362
b1 7
1$
#363
0$
#364
b10 7
1$
#365
0$
#366
b11111 8
b0 "
b0 1
b10000 !
b10000 6
b0 0
1*
b0 7
1$
#367
0$
#368
b1 7
1$
#369
0$
#370
b10 7
1$
#371
0$
#372
0*
b0 7
1$
#373
0$
#374
b1 7
1$
#375
0$
#376
b10 7
1$
#377
0$
#378
b111111 "
b111111 1
b1 !
b1 6
b1 0
b100000 8
1*
b0 7
1$
#379
0$
#380
b1 7
1$
#381
0$
#382
b10 7
1$
#383
0$
#384
0*
b0 7
1$
#385
0$
#386
b1 7
1$
#387
0$
#388
b10 7
1$
#389
0$
#390
b100001 8
b10 !
b10 6
b10 0
1*
b0 7
1$
#391
0$
#392
b1 7
1$
#393
0$
#394
b10 7
1$
#395
0$
#396
0*
b0 7
1$
#397
0$
#398
b1 7
1$
#399
0$
#400
b10 7
1$
#401
0$
#402
b100 !
b100 6
b11 0
b100010 8
1*
b0 7
1$
#403
0$
#404
b1 7
1$
#405
0$
#406
b10 7
1$
#407
0$
#408
0*
b0 7
1$
#409
0$
#410
b1 7
1$
#411
0$
#412
b10 7
1$
#413
0$
#414
b100011 8
b1000 !
b1000 6
b100 0
1*
b0 7
1$
#415
0$
#416
b1 7
1$
#417
0$
#418
b10 7
1$
#419
0$
#420
0*
b0 7
1$
#421
0$
#422
b1 7
1$
#423
0$
#424
b10 7
1$
#425
0$
#426
b0 "
b0 1
b10000 !
b10000 6
b0 0
b100100 8
1*
b0 7
1$
#427
0$
#428
b1 7
1$
#429
0$
#430
b10 7
1$
#431
0$
#432
0*
b0 7
1$
#433
0$
#434
b1 7
1$
#435
0$
#436
b10 7
1$
#437
0$
#438
b100101 8
b111111 "
b111111 1
b1 !
b1 6
b1 0
1*
b0 7
1$
#439
0$
#440
b1 7
1$
#441
0$
#442
b10 7
1$
#443
0$
#444
0*
b0 7
1$
#445
0$
#446
b1 7
1$
#447
0$
#448
b10 7
1$
#449
0$
#450
b10 !
b10 6
b10 0
b100110 8
1*
b0 7
1$
#451
0$
#452
b1 7
1$
#453
0$
#454
b10 7
1$
#455
0$
#456
0*
b0 7
1$
#457
0$
#458
b1 7
1$
#459
0$
#460
b10 7
1$
#461
0$
#462
b100111 8
b100 !
b100 6
b11 0
1*
b0 7
1$
#463
0$
#464
b1 7
1$
#465
0$
#466
b10 7
1$
#467
0$
#468
0*
b0 7
1$
#469
0$
#470
b1 7
1$
#471
0$
#472
b10 7
1$
#473
0$
#474
b1000 !
b1000 6
b100 0
b101000 8
1*
b0 7
1$
#475
0$
#476
b1 7
1$
#477
0$
#478
b10 7
1$
#479
0$
#480
0*
b0 7
1$
#481
0$
#482
b1 7
1$
#483
0$
#484
b10 7
1$
#485
0$
#486
b1 #
b1 /
b110 2
b1 &
0,
b1 9
1+
b0 8
b0 "
b0 1
b10000 !
b10000 6
b0 0
1*
b0 7
1$
#487
0$
#488
b1 7
1$
#489
0$
#490
b10 7
1$
#491
0$
#492
0*
b0 7
1$
#493
0$
#494
b1 7
1$
#495
0$
#496
b10 7
1$
#497
0$
#498
b110 "
b110 1
b1 !
b1 6
b1 0
b1 8
1*
b0 7
1$
#499
0$
#500
b1 7
1$
#501
0$
#502
b10 7
1$
#503
0$
#504
0*
b0 7
1$
#505
0$
#506
b1 7
1$
#507
0$
#508
b10 7
1$
#509
0$
#510
b10 8
b111111 "
b111111 1
b10 !
b10 6
b10 0
1*
b0 7
1$
#511
0$
#512
b1 7
1$
#513
0$
#514
b10 7
1$
#515
0$
#516
0*
b0 7
1$
#517
0$
#518
b1 7
1$
#519
0$
#520
b10 7
1$
#521
0$
#522
b100 !
b100 6
b11 0
b11 8
1*
b0 7
1$
#523
0$
#524
b1 7
1$
#525
0$
#526
b10 7
1$
#527
0$
#528
0*
b0 7
1$
#529
0$
#530
b1 7
1$
#531
0$
#532
b10 7
1$
#533
0$
#534
b100 8
b1000 !
b1000 6
b100 0
1*
b0 7
1$
#535
0$
#536
b1 7
1$
#537
0$
#538
b10 7
1$
#539
0$
#540
0*
b0 7
1$
#541
0$
#542
b1 7
1$
#543
0$
#544
b10 7
1$
#545
0$
#546
b11 "
b11 1
b10000 !
b10000 6
b0 0
b101 8
1*
b0 7
1$
#547
0$
#548
b1 7
1$
#549
0$
#550
b10 7
1$
#551
0$
#552
0*
b0 7
1$
#553
0$
#554
b1 7
1$
#555
0$
#556
b10 7
1$
#557
0$
#558
b110 8
b110 "
b110 1
b1 !
b1 6
b1 0
1*
b0 7
1$
#559
0$
#560
b1 7
1$
#561
0$
#562
b10 7
1$
#563
0$
#564
0*
b0 7
1$
#565
0$
#566
b1 7
1$
#567
0$
#568
b10 7
1$
#569
0$
#570
b111111 "
b111111 1
b10 !
b10 6
b10 0
b111 8
1*
b0 7
1$
#571
0$
#572
b1 7
1$
#573
0$
#574
b10 7
1$
#575
0$
#576
0*
b0 7
1$
#577
0$
#578
b1 7
1$
#579
0$
#580
b10 7
1$
#581
0$
#582
b1000 8
b100 !
b100 6
b11 0
1*
b0 7
1$
#583
0$
#584
b1 7
1$
#585
0$
#586
b10 7
1$
#587
0$
#588
0*
b0 7
1$
#589
0$
#590
b1 7
1$
#591
0$
#592
b10 7
1$
#593
0$
#594
b1000 !
b1000 6
b100 0
b1001 8
1*
b0 7
1$
#595
0$
#596
b1 7
1$
#597
0$
#598
b10 7
1$
#599
0$
#600
0*
b0 7
1$
#601
0$
#602
b1 7
1$
#603
0$
#604
b10 7
1$
#605
0$
#606
b1010 8
b11 "
b11 1
b10000 !
b10000 6
b0 0
1*
b0 7
1$
#607
0$
#608
b1 7
1$
#609
0$
#610
b10 7
1$
#611
0$
#612
0*
b0 7
1$
#613
0$
#614
b1 7
1$
#615
0$
#616
b10 7
1$
#617
0$
#618
b110 "
b110 1
b1 !
b1 6
b1 0
b1011 8
1*
b0 7
1$
#619
0$
#620
b1 7
1$
#621
0$
#622
b10 7
1$
#623
0$
#624
0*
b0 7
1$
#625
0$
#626
b1 7
1$
#627
0$
#628
b10 7
1$
#629
0$
#630
b1100 8
b111111 "
b111111 1
b10 !
b10 6
b10 0
1*
b0 7
1$
#631
0$
#632
b1 7
1$
#633
0$
#634
b10 7
1$
#635
0$
#636
0*
b0 7
1$
#637
0$
#638
b1 7
1$
#639
0$
#640
b10 7
1$
#641
0$
#642
b100 !
b100 6
b11 0
b1101 8
1*
b0 7
1$
#643
0$
#644
b1 7
1$
#645
0$
#646
b10 7
1$
#647
0$
#648
0*
b0 7
1$
#649
0$
#650
b1 7
1$
#651
0$
#652
b10 7
1$
#653
0$
#654
b1110 8
b1000 !
b1000 6
b100 0
1*
b0 7
1$
#655
0$
#656
b1 7
1$
#657
0$
#658
b10 7
1$
#659
0$
#660
0*
b0 7
1$
#661
0$
#662
b1 7
1$
#663
0$
#664
b10 7
1$
#665
0$
#666
b11 "
b11 1
b10000 !
b10000 6
b0 0
b1111 8
1*
b0 7
1$
#667
0$
#668
b1 7
1$
#669
0$
#670
b10 7
1$
#671
0$
#672
0*
b0 7
1$
#673
0$
#674
b1 7
1$
#675
0$
#676
b10 7
1$
#677
0$
#678
b10000 8
b110 "
b110 1
b1 !
b1 6
b1 0
1*
b0 7
1$
#679
0$
#680
b1 7
1$
#681
0$
#682
b10 7
1$
#683
0$
#684
0*
b0 7
1$
#685
0$
#686
b1 7
1$
#687
0$
#688
b10 7
1$
#689
0$
#690
b111111 "
b111111 1
b10 !
b10 6
b10 0
b10001 8
1*
b0 7
1$
#691
0$
#692
b1 7
1$
#693
0$
#694
b10 7
1$
#695
0$
#696
0*
b0 7
1$
#697
0$
#698
b1 7
1$
#699
0$
#700
b10 7
1$
#701
0$
#702
b10010 8
b100 !
b100 6
b11 0
1*
b0 7
1$
#703
0$
#704
b1 7
1$
#705
0$
#706
b10 7
1$
#707
0$
#708
0*
b0 7
1$
#709
0$
#710
b1 7
1$
#711
0$
#712
b10 7
1$
#713
0$
#714
b1000 !
b1000 6
b100 0
b10011 8
1*
b0 7
1$
#715
0$
#716
b1 7
1$
#717
0$
#718
b10 7
1$
#719
0$
#720
0*
b0 7
1$
#721
0$
#722
b1 7
1$
#723
0$
#724
b10 7
1$
#725
0$
#726
b10100 8
b11 "
b11 1
b10000 !
b10000 6
b0 0
1*
b0 7
1$
#727
0$
#728
b1 7
1$
#729
0$
#730
b10 7
1$
#731
0$
#732
0*
b0 7
1$
#733
0$
#734
b1 7
1$
#735
0$
#736
b10 7
1$
#737
0$
#738
b110 "
b110 1
b1 !
b1 6
b1 0
b10101 8
1*
b0 7
1$
#739
0$
#740
b1 7
1$
#741
0$
#742
b10 7
1$
#743
0$
#744
0*
b0 7
1$
#745
0$
#746
b1 7
1$
#747
0$
#748
b10 7
1$
#749
0$
#750
b10110 8
b111111 "
b111111 1
b10 !
b10 6
b10 0
1*
b0 7
1$
#751
0$
#752
b1 7
1$
#753
0$
#754
b10 7
1$
#755
0$
#756
0*
b0 7
1$
#757
0$
#758
b1 7
1$
#759
0$
#760
b10 7
1$
#761
0$
#762
b100 !
b100 6
b11 0
b10111 8
1*
b0 7
1$
#763
0$
#764
b1 7
1$
#765
0$
#766
b10 7
1$
#767
0$
#768
0*
b0 7
1$
#769
0$
#770
b1 7
1$
#771
0$
#772
b10 7
1$
#773
0$
#774
b11000 8
b1000 !
b1000 6
b100 0
1*
b0 7
1$
#775
0$
#776
b1 7
1$
#777
0$
#778
b10 7
1$
#779
0$
#780
0*
b0 7
1$
#781
0$
#782
b1 7
1$
#783
0$
#784
b10 7
1$
#785
0$
#786
b11 "
b11 1
b10000 !
b10000 6
b0 0
b11001 8
1*
b0 7
1$
#787
0$
#788
b1 7
1$
#789
0$
#790
b10 7
1$
#791
0$
#792
0*
b0 7
1$
#793
0$
#794
b1 7
1$
#795
0$
#796
b10 7
1$
#797
0$
#798
b11010 8
b110 "
b110 1
b1 !
b1 6
b1 0
1*
b0 7
1$
#799
0$
#800
b1 7
1$
#801
0$
#802
b10 7
1$
#803
0$
#804
0*
b0 7
1$
#805
0$
#806
b1 7
1$
#807
0$
#808
b10 7
1$
#809
0$
#810
b111111 "
b111111 1
b10 !
b10 6
b10 0
b11011 8
1*
b0 7
1$
#811
0$
#812
b1 7
1$
#813
0$
#814
b10 7
1$
#815
0$
#816
0*
b0 7
1$
#817
0$
#818
b1 7
1$
#819
0$
#820
b10 7
1$
#821
0$
#822
b11100 8
b100 !
b100 6
b11 0
1*
b0 7
1$
#823
0$
#824
b1 7
1$
#825
0$
#826
b10 7
1$
#827
0$
#828
0*
b0 7
1$
#829
0$
#830
b1 7
1$
#831
0$
#832
b10 7
1$
#833
0$
#834
b1000 !
b1000 6
b100 0
b11101 8
1*
b0 7
1$
#835
0$
#836
b1 7
1$
#837
0$
#838
b10 7
1$
#839
0$
#840
0*
b0 7
1$
#841
0$
#842
b1 7
1$
#843
0$
#844
b10 7
1$
#845
0$
#846
b11110 8
b11 "
b11 1
b10000 !
b10000 6
b0 0
1*
b0 7
1$
#847
0$
#848
b1 7
1$
#849
0$
#850
b10 7
1$
#851
0$
#852
0*
b0 7
1$
#853
0$
#854
b1 7
1$
#855
0$
#856
b10 7
1$
#857
0$
#858
b110 "
b110 1
b1 !
b1 6
b1 0
b11111 8
1*
b0 7
1$
#859
0$
#860
b1 7
1$
#861
0$
#862
b10 7
1$
#863
0$
#864
0*
b0 7
1$
#865
0$
#866
b1 7
1$
#867
0$
#868
b10 7
1$
#869
0$
#870
b100000 8
b111111 "
b111111 1
b10 !
b10 6
b10 0
1*
b0 7
1$
#871
0$
#872
b1 7
1$
#873
0$
#874
b10 7
1$
#875
0$
#876
0*
b0 7
1$
#877
0$
#878
b1 7
1$
#879
0$
#880
b10 7
1$
#881
0$
#882
b100 !
b100 6
b11 0
b100001 8
1*
b0 7
1$
#883
0$
#884
b1 7
1$
#885
0$
#886
b10 7
1$
#887
0$
#888
0*
b0 7
1$
#889
0$
#890
b1 7
1$
#891
0$
#892
b10 7
1$
#893
0$
#894
b100010 8
b1000 !
b1000 6
b100 0
1*
b0 7
1$
#895
0$
#896
b1 7
1$
#897
0$
#898
b10 7
1$
#899
0$
#900
0*
b0 7
1$
#901
0$
#902
b1 7
1$
#903
0$
#904
b10 7
1$
#905
0$
#906
b11 "
b11 1
b10000 !
b10000 6
b0 0
b100011 8
1*
b0 7
1$
#907
0$
#908
b1 7
1$
#909
0$
#910
b10 7
1$
#911
0$
#912
0*
b0 7
1$
#913
0$
#914
b1 7
1$
#915
0$
#916
b10 7
1$
#917
0$
#918
b100100 8
b110 "
b110 1
b1 !
b1 6
b1 0
1*
b0 7
1$
#919
0$
#920
b1 7
1$
#921
0$
#922
b10 7
1$
#923
0$
#924
0*
b0 7
1$
#925
0$
#926
b1 7
1$
#927
0$
#928
b10 7
1$
#929
0$
